<?xml version="1.0"?>
<root>
<Feb-20>
<item row="1"><region_name>East Anglia</region_name><yr_month>Feb-20</yr_month><home_starter>233497</home_starter><emp_full_time>34841</emp_full_time><affordability_index>113</affordability_index><item0><id>15</id><reg_name>East Anglia</reg_name><prop_type>Detached</prop_type><adj_avg_price_ty>2894</adj_avg_price_ty><percent_cg>-2.7</percent_cg><uk_avg_price_ty>2536.6363636363635</uk_avg_price_ty></item0><item1><id>15</id><reg_name>East Anglia</reg_name><prop_type>Flats</prop_type><adj_avg_price_ty>3953</adj_avg_price_ty><percent_cg>2.57</percent_cg><uk_avg_price_ty>3193.3636363636365</uk_avg_price_ty></item1><item2><id>15</id><reg_name>East Anglia</reg_name><prop_type>Semis</prop_type><adj_avg_price_ty>2946</adj_avg_price_ty><percent_cg>-1.65</percent_cg><uk_avg_price_ty>2549</uk_avg_price_ty></item2><item3><id>15</id><reg_name>East Anglia</reg_name><prop_type>Terraced</prop_type><adj_avg_price_ty>2974</adj_avg_price_ty><percent_cg>-4.44</percent_cg><uk_avg_price_ty>2522.7272727272725</uk_avg_price_ty></item3></item>

<item row="2"><region_name>East Midlands</region_name><yr_month>Feb-20</yr_month><home_starter>156581</home_starter><emp_full_time>29791</emp_full_time><affordability_index>89</affordability_index><item0><id>6</id><reg_name>East Midlands</reg_name><prop_type>Detached</prop_type><adj_avg_price_ty>2205</adj_avg_price_ty><percent_cg>9.26</percent_cg><uk_avg_price_ty>2536.6363636363635</uk_avg_price_ty></item0><item1><id>6</id><reg_name>East Midlands</reg_name><prop_type>Flats</prop_type><adj_avg_price_ty>2184</adj_avg_price_ty><percent_cg>-5.11</percent_cg><uk_avg_price_ty>3193.3636363636365</uk_avg_price_ty></item1><item2><id>6</id><reg_name>East Midlands</reg_name><prop_type>Semis</prop_type><adj_avg_price_ty>2108</adj_avg_price_ty><percent_cg>1.88</percent_cg><uk_avg_price_ty>2549</uk_avg_price_ty></item2><item3><id>6</id><reg_name>East Midlands</reg_name><prop_type>Terraced</prop_type><adj_avg_price_ty>2185</adj_avg_price_ty><percent_cg>8.72</percent_cg><uk_avg_price_ty>2522.7272727272725</uk_avg_price_ty></item3></item>

<item row="3"><region_name>Greater London</region_name><yr_month>Feb-20</yr_month><home_starter>425010</home_starter><emp_full_time>41977</emp_full_time><affordability_index>171</affordability_index><item0><id>9</id><reg_name>Greater London</reg_name><prop_type>Detached</prop_type><adj_avg_price_ty>4914</adj_avg_price_ty><percent_cg>3.33</percent_cg><uk_avg_price_ty>2536.6363636363635</uk_avg_price_ty></item0><item1><id>9</id><reg_name>Greater London</reg_name><prop_type>Flats</prop_type><adj_avg_price_ty>6822</adj_avg_price_ty><percent_cg>-3.75</percent_cg><uk_avg_price_ty>3193.3636363636365</uk_avg_price_ty></item1><item2><id>9</id><reg_name>Greater London</reg_name><prop_type>Semis</prop_type><adj_avg_price_ty>5033</adj_avg_price_ty><percent_cg>-4.68</percent_cg><uk_avg_price_ty>2549</uk_avg_price_ty></item2><item3><id>9</id><reg_name>Greater London</reg_name><prop_type>Terraced</prop_type><adj_avg_price_ty>5185</adj_avg_price_ty><percent_cg>3.06</percent_cg><uk_avg_price_ty>2522.7272727272725</uk_avg_price_ty></item3></item>

<item row="4"><region_name>North East</region_name><yr_month>Feb-20</yr_month><home_starter>123571</home_starter><emp_full_time>28322</emp_full_time><affordability_index>74</affordability_index><item0><id>5</id><reg_name>North East</reg_name><prop_type>Detached</prop_type><adj_avg_price_ty>1910</adj_avg_price_ty><percent_cg>10.31</percent_cg><uk_avg_price_ty>2536.6363636363635</uk_avg_price_ty></item0><item1><id>5</id><reg_name>North East</reg_name><prop_type>Flats</prop_type><adj_avg_price_ty>2057</adj_avg_price_ty><percent_cg>10.74</percent_cg><uk_avg_price_ty>3193.3636363636365</uk_avg_price_ty></item1><item2><id>5</id><reg_name>North East</reg_name><prop_type>Semis</prop_type><adj_avg_price_ty>1739</adj_avg_price_ty><percent_cg>1.67</percent_cg><uk_avg_price_ty>2549</uk_avg_price_ty></item2><item3><id>5</id><reg_name>North East</reg_name><prop_type>Terraced</prop_type><adj_avg_price_ty>1635</adj_avg_price_ty><percent_cg>0.06</percent_cg><uk_avg_price_ty>2522.7272727272725</uk_avg_price_ty></item3></item>

<item row="5"><region_name>North West</region_name><yr_month>Feb-20</yr_month><home_starter>145293</home_starter><emp_full_time>30414</emp_full_time><affordability_index>81</affordability_index><item0><id>8</id><reg_name>North West</reg_name><prop_type>Detached</prop_type><adj_avg_price_ty>2202</adj_avg_price_ty><percent_cg>2.22</percent_cg><uk_avg_price_ty>2536.6363636363635</uk_avg_price_ty></item0><item1><id>8</id><reg_name>North West</reg_name><prop_type>Flats</prop_type><adj_avg_price_ty>2491</adj_avg_price_ty><percent_cg>4.8</percent_cg><uk_avg_price_ty>3193.3636363636365</uk_avg_price_ty></item1><item2><id>8</id><reg_name>North West</reg_name><prop_type>Semis</prop_type><adj_avg_price_ty>1964</adj_avg_price_ty><percent_cg>5.22</percent_cg><uk_avg_price_ty>2549</uk_avg_price_ty></item2><item3><id>8</id><reg_name>North West</reg_name><prop_type>Terraced</prop_type><adj_avg_price_ty>2030</adj_avg_price_ty><percent_cg>3.01</percent_cg><uk_avg_price_ty>2522.7272727272725</uk_avg_price_ty></item3></item>

<item row="6"><region_name>Scotland</region_name><yr_month>Feb-20</yr_month><home_starter>153544</home_starter><emp_full_time>31940</emp_full_time><affordability_index>81</affordability_index><item0><id>10</id><reg_name>Scotland</reg_name><prop_type>Detached</prop_type><adj_avg_price_ty>1783</adj_avg_price_ty><percent_cg>-0.62</percent_cg><uk_avg_price_ty>2536.6363636363635</uk_avg_price_ty></item0><item1><id>10</id><reg_name>Scotland</reg_name><prop_type>Flats</prop_type><adj_avg_price_ty>2315</adj_avg_price_ty><percent_cg>-4.1</percent_cg><uk_avg_price_ty>3193.3636363636365</uk_avg_price_ty></item1><item2><id>10</id><reg_name>Scotland</reg_name><prop_type>Semis</prop_type><adj_avg_price_ty>1984</adj_avg_price_ty><percent_cg>7.53</percent_cg><uk_avg_price_ty>2549</uk_avg_price_ty></item2><item3><id>10</id><reg_name>Scotland</reg_name><prop_type>Terraced</prop_type><adj_avg_price_ty>2212</adj_avg_price_ty><percent_cg>4.34</percent_cg><uk_avg_price_ty>2522.7272727272725</uk_avg_price_ty></item3></item>

<item row="7"><region_name>South East</region_name><yr_month>Feb-20</yr_month><home_starter>252619</home_starter><emp_full_time>37024</emp_full_time><affordability_index>115</affordability_index><item0><id>1</id><reg_name>South East</reg_name><prop_type>Detached</prop_type><adj_avg_price_ty>3460</adj_avg_price_ty><percent_cg>0.97</percent_cg><uk_avg_price_ty>2536.6363636363635</uk_avg_price_ty></item0><item1><id>1</id><reg_name>South East</reg_name><prop_type>Flats</prop_type><adj_avg_price_ty>3962</adj_avg_price_ty><percent_cg>-1.2</percent_cg><uk_avg_price_ty>3193.3636363636365</uk_avg_price_ty></item1><item2><id>1</id><reg_name>South East</reg_name><prop_type>Semis</prop_type><adj_avg_price_ty>3509</adj_avg_price_ty><percent_cg>2.31</percent_cg><uk_avg_price_ty>2549</uk_avg_price_ty></item2><item3><id>1</id><reg_name>South East</reg_name><prop_type>Terraced</prop_type><adj_avg_price_ty>3357</adj_avg_price_ty><percent_cg>1.41</percent_cg><uk_avg_price_ty>2522.7272727272725</uk_avg_price_ty></item3></item>

<item row="8"><region_name>South West</region_name><yr_month>Feb-20</yr_month><home_starter>197178</home_starter><emp_full_time>30564</emp_full_time><affordability_index>109</affordability_index><item0><id>2</id><reg_name>South West</reg_name><prop_type>Detached</prop_type><adj_avg_price_ty>2589</adj_avg_price_ty><percent_cg>-2</percent_cg><uk_avg_price_ty>2536.6363636363635</uk_avg_price_ty></item0><item1><id>2</id><reg_name>South West</reg_name><prop_type>Flats</prop_type><adj_avg_price_ty>3356</adj_avg_price_ty><percent_cg>11.41</percent_cg><uk_avg_price_ty>3193.3636363636365</uk_avg_price_ty></item1><item2><id>2</id><reg_name>South West</reg_name><prop_type>Semis</prop_type><adj_avg_price_ty>2591</adj_avg_price_ty><percent_cg>4.83</percent_cg><uk_avg_price_ty>2549</uk_avg_price_ty></item2><item3><id>2</id><reg_name>South West</reg_name><prop_type>Terraced</prop_type><adj_avg_price_ty>2511</adj_avg_price_ty><percent_cg>2.17</percent_cg><uk_avg_price_ty>2522.7272727272725</uk_avg_price_ty></item3></item>

<item row="9"><region_name>Wales</region_name><yr_month>Feb-20</yr_month><home_starter>148564</home_starter><emp_full_time>28899</emp_full_time><affordability_index>87</affordability_index><item0><id>11</id><reg_name>Wales</reg_name><prop_type>Detached</prop_type><adj_avg_price_ty>1448</adj_avg_price_ty><percent_cg>-9</percent_cg><uk_avg_price_ty>2536.6363636363635</uk_avg_price_ty></item0><item1><id>11</id><reg_name>Wales</reg_name><prop_type>Flats</prop_type><adj_avg_price_ty>2509</adj_avg_price_ty><percent_cg>6.38</percent_cg><uk_avg_price_ty>3193.3636363636365</uk_avg_price_ty></item1><item2><id>11</id><reg_name>Wales</reg_name><prop_type>Semis</prop_type><adj_avg_price_ty>1895</adj_avg_price_ty><percent_cg>2.53</percent_cg><uk_avg_price_ty>2549</uk_avg_price_ty></item2><item3><id>11</id><reg_name>Wales</reg_name><prop_type>Terraced</prop_type><adj_avg_price_ty>2020</adj_avg_price_ty><percent_cg>17.3</percent_cg><uk_avg_price_ty>2522.7272727272725</uk_avg_price_ty></item3></item>

<item row="10"><region_name>West Midlands</region_name><yr_month>Feb-20</yr_month><home_starter>174592</home_starter><emp_full_time>30256</emp_full_time><affordability_index>97</affordability_index><item0><id>4</id><reg_name>West Midlands</reg_name><prop_type>Detached</prop_type><adj_avg_price_ty>2399</adj_avg_price_ty><percent_cg>4.35</percent_cg><uk_avg_price_ty>2536.6363636363635</uk_avg_price_ty></item0><item1><id>4</id><reg_name>West Midlands</reg_name><prop_type>Flats</prop_type><adj_avg_price_ty>2842</adj_avg_price_ty><percent_cg>-5.54</percent_cg><uk_avg_price_ty>3193.3636363636365</uk_avg_price_ty></item1><item2><id>4</id><reg_name>West Midlands</reg_name><prop_type>Semis</prop_type><adj_avg_price_ty>2300</adj_avg_price_ty><percent_cg>3.98</percent_cg><uk_avg_price_ty>2549</uk_avg_price_ty></item2><item3><id>4</id><reg_name>West Midlands</reg_name><prop_type>Terraced</prop_type><adj_avg_price_ty>1687</adj_avg_price_ty><percent_cg>-28.23</percent_cg><uk_avg_price_ty>2522.7272727272725</uk_avg_price_ty></item3></item>

<item row="11"><region_name>Yorkshire and the Humber</region_name><yr_month>Feb-20</yr_month><home_starter>144396</home_starter><emp_full_time>29445</emp_full_time><affordability_index>83</affordability_index><item0><id>7</id><reg_name>Yorkshire and the Humber</reg_name><prop_type>Detached</prop_type><adj_avg_price_ty>2099</adj_avg_price_ty><percent_cg>4.6</percent_cg><uk_avg_price_ty>2536.6363636363635</uk_avg_price_ty></item0><item1><id>7</id><reg_name>Yorkshire and the Humber</reg_name><prop_type>Flats</prop_type><adj_avg_price_ty>2636</adj_avg_price_ty><percent_cg>22.96</percent_cg><uk_avg_price_ty>3193.3636363636365</uk_avg_price_ty></item1><item2><id>7</id><reg_name>Yorkshire and the Humber</reg_name><prop_type>Semis</prop_type><adj_avg_price_ty>1970</adj_avg_price_ty><percent_cg>9.91</percent_cg><uk_avg_price_ty>2549</uk_avg_price_ty></item2><item3><id>7</id><reg_name>Yorkshire and the Humber</reg_name><prop_type>Terraced</prop_type><adj_avg_price_ty>1954</adj_avg_price_ty><percent_cg>6.11</percent_cg><uk_avg_price_ty>2522.7272727272725</uk_avg_price_ty></item3></item>
</Feb-20>
</root>
